[{"line":1,"elements":[{"line":3,"name":"Database baglantisi kurar","description":"","type":"background","keyword":"Background","steps":[{"result":{"duration":1099183000,"status":"passed"},"line":4,"name":"Database connection kurar","match":{"location":"stepDefinitions.stepDefinition.database_connection_kurar()"},"keyword":"* "}]},{"start_timestamp":"2024-09-24T14:49:03.476Z","line":7,"name":"Deposits tablosunda amount degerine gore id sorgulama testi.","description":"","id":"select-query-execution;deposits-tablosunda-amount-degerine-gore-id-sorgulama-testi.","type":"scenario","keyword":"Scenario","steps":[{"result":{"duration":67698000,"status":"passed"},"line":9,"name":"Query01 hazirlar","match":{"location":"stepDefinitions.stepDefinition.query01_hazirlar()"},"keyword":"Given "},{"result":{"duration":3187000,"status":"passed"},"line":10,"name":"Query01 sonuclarini isler","match":{"location":"stepDefinitions.stepDefinition.query01_sonuclarini_isler()"},"keyword":"When "},{"result":{"duration":9852000,"status":"passed"},"line":11,"name":"Database baglantisini kapatir.","match":{"location":"stepDefinitions.stepDefinition.database_baglantisini_kapatir()"},"keyword":"And "}],"tags":[{"name":"@Query01"}]}],"name":"Select Query Execution","description":"","id":"select-query-execution","keyword":"Feature","uri":"file:src/test/resources/features/QueryFile.feature","tags":[]}]